<annotation>
	<folder>images12_forwardMandatoryDirection</folder>
	<filename>video12_246.png</filename>
	<path>D:\labelimg\labelimg_labeling\Forward Mandatory Direction Sign\images12_forwardMandatoryDirection\video12_246.png</path>
	<source>
		<database>Unknown</database>
	</source>
	<size>
		<width>848</width>
		<height>464</height>
		<depth>3</depth>
	</size>
	<segmented>0</segmented>
	<object>
		<name>forward</name>
		<pose>Unspecified</pose>
		<truncated>0</truncated>
		<difficult>0</difficult>
		<bndbox>
			<xmin>324</xmin>
			<ymin>87</ymin>
			<xmax>519</xmax>
			<ymax>281</ymax>
		</bndbox>
	</object>
</annotation>
